<?xml version="1.0" encoding="utf-8" ?>
<dwsync>
<file name="LostPassword.html" server="mobile-app.worldsecuresystems.com//" local="129698100000000000" remote="129698100000000000" Dst="2" />
<file name="Invoice.html" server="mobile-app.worldsecuresystems.com//" local="129698100000000000" remote="129698100000000000" Dst="2" />
<file name="Order.html" server="mobile-app.worldsecuresystems.com//" local="129698100000000000" remote="129698100000000000" Dst="2" />
<file name="Workflow3rdParty.html" server="mobile-app.worldsecuresystems.com//" local="129698100000000000" remote="129698100000000000" Dst="2" />
<file name="ForumPostSubscriberAlert.html" server="mobile-app.worldsecuresystems.com//" local="129698100000000000" remote="129698100000000000" Dst="2" />
<file name="ForumTopicSubscriberAlert.html" server="mobile-app.worldsecuresystems.com//" local="129698100000000000" remote="129698100000000000" Dst="2" />
<file name="DoubleOptInEmail.html" server="mobile-app.worldsecuresystems.com//" local="129698100000000000" remote="129698100000000000" Dst="2" />
<file name="SecureZoneDetails.html" server="mobile-app.worldsecuresystems.com//" local="129698100000000000" remote="129698100000000000" Dst="2" />
<file name="AffiliateProgramDetails.html" server="mobile-app.worldsecuresystems.com//" local="129698100000000000" remote="129698100000000000" Dst="2" />
<file name="GiftVoucherEmail.html" server="mobile-app.worldsecuresystems.com//" local="129698100000000000" remote="129698100000000000" Dst="2" />
<file name="DropShipping.html" server="mobile-app.worldsecuresystems.com//" local="129698100000000000" remote="129698100000000000" Dst="2" />
<file name="ReferAFriend.html" server="mobile-app.worldsecuresystems.com//" local="129698100000000000" remote="129698100000000000" Dst="2" />
<file name="CSF.html" server="mobile-app.worldsecuresystems.com//" local="129698100000000000" remote="129698100000000000" Dst="2" />
<file name="WorkflowNotification.html" server="mobile-app.worldsecuresystems.com//" local="130525721110000000" remote="130525721170000000" Dst="2" />
<file name="WorkflowTask.html" server="mobile-app.worldsecuresystems.com//" local="130525721110000000" remote="130525721170000000" Dst="2" />
<file name="WorkflowCompletion.html" server="mobile-app.worldsecuresystems.com//" local="130525721110000000" remote="130525721170000000" Dst="2" />
<file name="WorkflowReminder.html" server="mobile-app.worldsecuresystems.com//" local="130525721110000000" remote="130525721170000000" Dst="2" />
<file name="WorkflowEscalation.html" server="mobile-app.worldsecuresystems.com//" local="130525721110000000" remote="130525721170000000" Dst="2" />
<file name="WorkflowRejection.html" server="mobile-app.worldsecuresystems.com//" local="130525721110000000" remote="130525721170000000" Dst="2" />
<file name="AffiliateProgramDetails.html" server="mahzuusa.worldsecuresystems.com//" local="129698100000000000" remote="130525597420000000" Dst="2" />
<file name="CSF.html" server="mahzuusa.worldsecuresystems.com//" local="129698100000000000" remote="130525597430000000" Dst="2" />
<file name="DoubleOptInEmail.html" server="mahzuusa.worldsecuresystems.com//" local="129698100000000000" remote="130525597440000000" Dst="2" />
<file name="DropShipping.html" server="mahzuusa.worldsecuresystems.com//" local="129698100000000000" remote="130525597450000000" Dst="2" />
<file name="ForumPostSubscriberAlert.html" server="mahzuusa.worldsecuresystems.com//" local="129698100000000000" remote="130525597460000000" Dst="2" />
<file name="ForumTopicSubscriberAlert.html" server="mahzuusa.worldsecuresystems.com//" local="129698100000000000" remote="130525597460000000" Dst="2" />
<file name="GiftVoucherEmail.html" server="mahzuusa.worldsecuresystems.com//" local="129698100000000000" remote="130525597470000000" Dst="2" />
<file name="Invoice.html" server="mahzuusa.worldsecuresystems.com//" local="129698100000000000" remote="130525597480000000" Dst="2" />
<file name="LostPassword.html" server="mahzuusa.worldsecuresystems.com//" local="129698100000000000" remote="130525597490000000" Dst="2" />
<file name="Order.html" server="mahzuusa.worldsecuresystems.com//" local="129698100000000000" remote="130525597500000000" Dst="2" />
<file name="ReferAFriend.html" server="mahzuusa.worldsecuresystems.com//" local="129698100000000000" remote="130525597600000000" Dst="2" />
<file name="SecureZoneDetails.html" server="mahzuusa.worldsecuresystems.com//" local="129698100000000000" remote="130525597600000000" Dst="2" />
<file name="Workflow3rdParty.html" server="mahzuusa.worldsecuresystems.com//" local="129698100000000000" remote="130525597610000000" Dst="2" />
<file name="WorkflowCompletion.html" server="mahzuusa.worldsecuresystems.com//" local="130525563130000000" remote="130525597620000000" Dst="2" />
<file name="WorkflowEscalation.html" server="mahzuusa.worldsecuresystems.com//" local="130525563130000000" remote="130525597620000000" Dst="2" />
<file name="WorkflowNotification.html" server="mahzuusa.worldsecuresystems.com//" local="130525563130000000" remote="130525597630000000" Dst="2" />
<file name="WorkflowRejection.html" server="mahzuusa.worldsecuresystems.com//" local="130525563130000000" remote="130525597640000000" Dst="2" />
<file name="WorkflowReminder.html" server="mahzuusa.worldsecuresystems.com//" local="130525563130000000" remote="130525597650000000" Dst="2" />
<file name="WorkflowTask.html" server="mahzuusa.worldsecuresystems.com//" local="130525563130000000" remote="130525597650000000" Dst="2" />
</dwsync>