<?xml version="1.0" encoding="utf-8" ?>
<dwsync>
<file name="cbi.css" server="mobile-app.worldsecuresystems.com//" local="130460465540000000" remote="130460465540000000" Dst="2" />
<file name="cbi.min.css" server="mobile-app.worldsecuresystems.com//" local="130460465580000000" remote="130460465580000000" Dst="2" />
<file name="jquery.mobile.icons.min.css" server="mobile-app.worldsecuresystems.com//" local="130460468240000000" remote="130460468240000000" Dst="2" />
<file name="jquery.mobile.structure-1.0.min.css" server="mobile-app.worldsecuresystems.com//" local="130460468270000000" remote="130460468270000000" Dst="2" />
<file name="jquery.mobile.theme-1.0.min.css" server="mobile-app.worldsecuresystems.com//" local="130460468380000000" remote="130460468380000000" Dst="2" />
<file name="jquery.mobile-1.0.min.js" server="mobile-app.worldsecuresystems.com//" local="130460468180000000" remote="130460468180000000" Dst="2" />
<file name="jquery-1.6.4.min.js" server="mobile-app.worldsecuresystems.com//" local="130460468140000000" remote="130460468140000000" Dst="2" />
<file name="cbi.css" server="mahzuusa.worldsecuresystems.com//" local="130460465540000000" remote="130525595400000000" Dst="2" />
<file name="cbi.min.css" server="mahzuusa.worldsecuresystems.com//" local="130460465580000000" remote="130525595410000000" Dst="2" />
<file name="jquery-1.6.4.min.js" server="mahzuusa.worldsecuresystems.com//" local="130460468140000000" remote="130525596370000000" Dst="2" />
<file name="jquery.mobile-1.0.min.js" server="mahzuusa.worldsecuresystems.com//" local="130460468180000000" remote="130525596390000000" Dst="2" />
<file name="jquery.mobile.icons.min.css" server="mahzuusa.worldsecuresystems.com//" local="130460468240000000" remote="130525596410000000" Dst="2" />
<file name="jquery.mobile.structure-1.0.min.css" server="mahzuusa.worldsecuresystems.com//" local="130460468270000000" remote="130525596430000000" Dst="2" />
<file name="jquery.mobile.theme-1.0.min.css" server="mahzuusa.worldsecuresystems.com//" local="130460468380000000" remote="130525596440000000" Dst="2" />
</dwsync>